tweet_generator/__init__.py
tweet_generator/tweet_generator.py
tweet_generator-0.0.31.dist-info/DESCRIPTION.rst
tweet_generator-0.0.31.dist-info/METADATA
tweet_generator-0.0.31.dist-info/RECORD
tweet_generator-0.0.31.dist-info/WHEEL
tweet_generator-0.0.31.dist-info/metadata.json
tweet_generator-0.0.31.dist-info/top_level.txt
