Metadata-Version: 2.0
Name: tweet-generator
Version: 0.0.31
Summary: Package for generating randomized tweets of a user on twitter.
Home-page: https://github.com/oliviersm199
Author: Olivier Simard-Morissette
Author-email: olivier.morissette@gmail.com
License: MIT
Platform: UNKNOWN
Classifier: License :: OSI Approved :: GNU General Public License v3 (GPLv3)
Classifier: Programming Language :: Python
Classifier: Programming Language :: Python :: 3
Classifier: Programming Language :: Python :: 3.6
Classifier: Programming Language :: Python :: Implementation :: CPython
Classifier: Programming Language :: Python :: Implementation :: PyPy
Requires-Python: >=3.6.0
Requires-Dist: oauthlib
Requires-Dist: requests
Requires-Dist: requests-oauthlib
Requires-Dist: tweepy
